LICENSE
MANIFEST.in
README.rst
requirements.txt
setup.py
docs/index.rst
saiorm/MySQL.py
saiorm/__init__.py
saiorm/base.py
saiorm/utility.py
saiorm/x_torndb.py
saiorm.egg-info/PKG-INFO
saiorm.egg-info/SOURCES.txt
saiorm.egg-info/dependency_links.txt
saiorm.egg-info/requires.txt
saiorm.egg-info/top_level.txt